isvg.py
isvg-1.0.3.dist-info/licenses/LICENSE
isvg-1.0.3.dist-info/METADATA
isvg-1.0.3.dist-info/WHEEL
isvg-1.0.3.dist-info/top_level.txt
isvg-1.0.3.dist-info/RECORD
