Metadata-Version: 2.4
Name: iSVG
Version: 1.0.3
Summary: Extends Markdown with support for inline SVG images.
Author-email: "M.P. van de Weerd" <michael@parcifal.dev>
License: LICENSE
Project-URL: Homepage, https://gitlab.com/parcifal/isvg
Project-URL: Bug Tracker, https://gitlab.com/parcifal/isvg/-/issues
Keywords: markdown,svg
Classifier: Development Status :: 5 - Production/Stable
Classifier: Intended Audience :: Developers
Classifier: License :: OSI Approved :: GNU General Public License v3 (GPLv3)
License-File: LICENSE
Requires-Dist: markdown
Dynamic: license-file
